<?xml version="1.0" encoding="utf-8"?>
<LanguageData>
  <!--The following translations were generated by https://www.deepl.com/-->
  <SLIR.logging.label>Activer la journalisation verbeuse</SLIR.logging.label>
  <SLIR.logging.tooltip>Affiche la journalisation détaillée, pour trouver les erreurs.</SLIR.logging.tooltip>
  <SLIR.version.label>Version installée du module : {0}</SLIR.version.label>
  <SLIR.animal.label>Animal</SLIR.animal.label>
  <SLIR.rotten.label>Rotten</SLIR.rotten.label>
  <SLIR.bone.label>Os</SLIR.bone.label>
  <SLIR.search>Recherche</SLIR.search>
  <SLIR.info.label>Sélectionnez les animaux qui devraient pouvoir manger des cadavres pourris ou desséchés.</SLIR.info.label>
</LanguageData>